odoo/addons/web_dark_mode/README.rst
odoo/addons/web_dark_mode/__init__.py
odoo/addons/web_dark_mode/__manifest__.py
odoo/addons/web_dark_mode/i18n/es.po
odoo/addons/web_dark_mode/i18n/es_AR.po
odoo/addons/web_dark_mode/i18n/fr.po
odoo/addons/web_dark_mode/i18n/hr.po
odoo/addons/web_dark_mode/i18n/it.po
odoo/addons/web_dark_mode/i18n/tr.po
odoo/addons/web_dark_mode/i18n/web_dark_mode.pot
odoo/addons/web_dark_mode/i18n/zh.po
odoo/addons/web_dark_mode/models/__init__.py
odoo/addons/web_dark_mode/models/ir_http.py
odoo/addons/web_dark_mode/models/res_users.py
odoo/addons/web_dark_mode/readme/CONTRIBUTORS.md
odoo/addons/web_dark_mode/readme/DESCRIPTION.md
odoo/addons/web_dark_mode/readme/ROADMAP.md
odoo/addons/web_dark_mode/static/description/icon.png
odoo/addons/web_dark_mode/static/description/index.html
odoo/addons/web_dark_mode/static/src/core/colorlist/colorlist.dark.scss
odoo/addons/web_dark_mode/static/src/core/notebook/notebook.dark.scss
odoo/addons/web_dark_mode/static/src/core/tags_list/tags_list.dark.scss
odoo/addons/web_dark_mode/static/src/js/switch_item.esm.js
odoo/addons/web_dark_mode/static/src/scss/bootstrap_overridden.dark.scss
odoo/addons/web_dark_mode/static/src/scss/bs_functions_overrides.dark.scss
odoo/addons/web_dark_mode/static/src/scss/primary_variables.dark.scss
odoo/addons/web_dark_mode/static/src/scss/secondary_variables.dark.scss
odoo/addons/web_dark_mode/static/src/search/search_panel/search_view.dark.scss
odoo/addons/web_dark_mode/static/src/views/calendar/calendar_renderer.dark.scss
odoo/addons/web_dark_mode/static/src/views/fields/image/image_field.dark.scss
odoo/addons/web_dark_mode/static/src/views/fields/properties/properties_field.dark.scss
odoo/addons/web_dark_mode/static/src/views/form/form_controller.dark.scss
odoo/addons/web_dark_mode/static/src/views/kanban/kanban_controller.dark.scss
odoo/addons/web_dark_mode/static/src/webclient/navbar/navbar.variables.dark.scss
odoo/addons/web_dark_mode/tests/__init__.py
odoo_addon_web_dark_mode-18.0.1.0.0.16.dist-info/METADATA
odoo_addon_web_dark_mode-18.0.1.0.0.16.dist-info/WHEEL
odoo_addon_web_dark_mode-18.0.1.0.0.16.dist-info/top_level.txt
odoo_addon_web_dark_mode-18.0.1.0.0.16.dist-info/RECORD
